setup.py
distb/Binomialdistribution.py
distb/Gaussiandistribution.py
distb/Generaldistribution.py
distb/__init__.py
distb.egg-info/PKG-INFO
distb.egg-info/SOURCES.txt
distb.egg-info/dependency_links.txt
distb.egg-info/not-zip-safe
distb.egg-info/top_level.txt